{"id": 46047, "song": "Tomorrow never world", "artist": "ゴールデンボンバー", "composer": "鬼龍院翔", "chord": ["D", "A", "G", "A", "D", "A", "F#7", "Bm", "G", "F#m7", "Bm", "Em", "A7", "D", "A", "Bm", "G", "F#m", "Em", "A7", "D", "A", "Bm", "G", "F#m", "Em", "A7", "F#m", "Bm", "Em", "A", "F#m", "Bm", "Em", "A", "D", "A", "F#7", "Bm", "A", "G", "F#m", "Bm", "G", "Gm", "A7", "D", "A", "G", "F#m", "F#", "Bm", "A", "G", "F#m", "Bm", "G", "Gm", "A", "D", "D", "A", "F#7", "Bm", "G", "F#m7", "Bm", "Em", "A7", "D", "A", "Bm", "G", "F#m", "Em", "A7", "F#m", "Bm", "Em", "A", "G", "F#m", "Bm", "Em", "A7", "D", "A", "G", "F#m", "F#7", "Bm", "A", "G", "F#m", "Bm", "G", "Gm", "A7", "D", "A", "G", "F#m", "F#7", "Bm", "A", "G", "F#m", "Bm", "G", "Gm", "A", "D", "D", "A", "F#7", "Bm", "G", "F#m7", "Bm", "Em", "A7", "B", "D#", "A#", "G7", "Cm", "A#", "G#", "Gm", "Cm", "G#", "G#m", "A#7", "D#", "A#", "G#", "Gm", "G", "Cm", "A#", "G#", "Gm", "Cm", "G#", "G#m", "A#", "D#", "D#", "A#", "G7", "Cm", "G#", "Gm7", "Cm", "G#", "A#7", "D#"]}