{"id": 23291, "song": "江戸の夜明け", "artist": "杉良太郎", "composer": "曽根幸明", "chord": ["Am", "G", "F", "Em7", "Am", "G", "Am", "G", "Am", "Dm", "Em", "Am", "Dm", "Em", "Am", "C", "F", "Em", "Am", "Dm", "Em", "Am", "Em", "Am", "F", "G", "Am", "Am", "G", "Am", "G", "Am", "G", "Am", "Dm", "Em", "Am", "Dm", "Em", "Am", "C", "F", "Em", "Am", "Dm", "Em", "Am", "Em", "Am", "F", "G", "Am", "Am", "G", "Am", "G", "F", "Em7", "Am", "G", "Am", "G", "Am", "Dm", "Em", "Am", "Dm", "Em", "Am", "C", "F", "Em", "Am", "Dm", "Em", "Am", "Em", "Am", "F", "G", "Am", "Am", "G", "Am", "G", "Am", "G", "Am"]}