{"id": 28980, "song": "夢見の森", "artist": "熊木杏里", "composer": "熊木杏里", "chord": ["Fmaj7", "Em7", "Dm7", "Cadd9", "Fmaj7", "Em7", "Dm7", "Cadd9", "Fmaj7", "Fm", "Cadd9", "Fmaj7", "Fm", "G", "Cadd9", "Am", "G", "F", "C", "F", "G", "Csus4", "C", "B♭", "F", "Cadd9", "Fmaj7", "Fm", "Cadd9", "Fmaj7", "Fm", "G", "Cadd9", "G", "F", "C", "G", "Am7", "Fmaj7", "Em7", "Dm7", "G", "F", "C", "F", "C", "F", "C", "G", "Am", "F", "C", "F", "C", "F", "C", "G", "Am", "F", "C", "B♭", "F", "Cadd9", "Fmaj7", "Fm", "Cadd9", "Fmaj7", "Fm", "G", "Cadd9", "G", "F", "C", "G", "Am7", "Fmaj7", "Em7", "Dm7", "G", "F", "C", "F", "C", "F", "C", "G", "Am", "F", "C", "F", "C", "F", "C", "G", "Am", "B♭", "F", "C", "E♭", "B♭", "F", "A♭", "E♭", "B♭", "Gsus4", "G", "F", "C", "F", "C", "F", "C", "G", "Am", "F", "C", "F", "C", "F", "C", "G", "Am", "F", "C", "F", "C", "F", "C", "G", "Am", "F", "C", "F", "C", "F", "C", "G", "Am", "F", "C", "F", "C", "F", "C", "B♭", "F", "C"]}