{"id": 85293, "song": "Addicted to love", "artist": "w-inds.", "composer": "REINAGLE DAMON JARED・Jimmy Burney II・FRANKS JUSTIN SCOTT", "chord": ["E♭m", "G♭", "D♭", "E♭m", "G♭", "D♭", "E♭m", "G♭", "D♭", "B", "B♭", "E♭m", "G♭", "D♭", "E♭m", "G♭", "D♭", "E♭m", "G♭", "D♭", "B", "B♭m", "E♭m", "G♭", "D♭", "E♭m", "G♭", "D♭", "E♭m", "G♭", "D♭", "B", "B♭m", "E♭m", "B", "G♭", "D♭", "E♭m", "B", "G♭", "D♭", "E♭m", "B", "G♭", "D♭", "E♭m", "B", "G♭", "D♭", "E♭m", "E♭m", "G♭", "D♭", "E♭m", "G♭", "D♭", "E♭m", "G♭", "D♭", "B", "B♭m", "E♭m", "G♭", "D♭", "E♭m", "G♭", "D♭", "E♭m", "G♭", "D♭", "B", "B♭m", "E♭m", "B", "G♭", "D♭", "E♭m", "B", "G♭", "D♭", "E♭m", "B", "G♭", "D♭", "E♭m", "B", "G♭", "D♭", "E♭m", "E♭m", "B", "A♭m", "B♭m", "E♭m", "B", "A♭m", "B♭", "Ddim", "E♭m", "B", "G♭", "D♭", "E♭m", "B", "G♭", "D♭", "E♭m", "B", "G♭", "D♭", "E♭m", "B", "G♭", "D♭", "E♭m"]}