{"id": 30236, "song": "SIX SHAME FACES～今夜も最高!!!!!!～", "artist": "VOICE by トト子(遠藤綾) feat.おそ松(櫻井孝宏)×カラ松(中村悠一)×チョロ松(神谷浩史)×一松(福山潤)×十四松(小野大輔)×トド松(入野自由)", "composer": "TECHNOBOYS PULCRAFT GREEN-FUND", "chord": ["Bm", "D", "Bm", "D", "Bm", "D", "Bm", "D", "Bm", "D", "G", "Bm", "Bm", "D", "G", "Bm", "Bm", "D", "Bm", "D", "Bm", "D", "G", "Bm", "D", "G", "F#7", "A", "G", "A", "G", "D", "Em7", "A", "F", "G♭", "G", "A♭", "A", "B♭7", "N.C", "E♭m", "E♭m", "Cm7-5", "C", "B♭7", "D♭", "E♭m", "Cm7-5", "B", "B♭7", "D♭", "E♭m", "E♭m", "Cm7-5", "B", "B♭7", "D♭", "E♭m", "Cm7-5", "B", "B♭7", "D♭", "E♭m", "N.C", "Bm", "D", "Bm", "D", "Bm", "D", "Bm", "D", "Bm", "D", "G", "Bm", "Bm", "D", "G", "Bm", "Bm", "D", "Bm", "D", "Bm", "D", "G", "Bm", "Bm", "D", "G", "F#7", "A", "G", "A", "G", "D", "Em7", "A", "F", "G♭", "G", "A♭", "A", "B♭7", "N.C", "E♭m", "E♭m", "Cm7-5", "B", "B♭7", "D♭", "E♭m", "Cm7-5", "B", "B♭7", "D♭", "E♭m", "E♭m", "Cm7-5", "B", "B♭7", "D♭", "E♭m", "Cm7-5", "B", "B♭7", "D♭", "E♭m", "E♭m", "D♭", "E♭m", "D♭", "E♭m", "D♭", "E♭m", "D♭", "E♭m", "D♭", "E♭m", "D♭", "E♭m", "D♭", "E♭m", "D♭", "A♭m7", "B♭m7", "D♭", "E♭m", "A♭m7", "B♭m7", "D♭", "G♭", "E♭m", "A♭m7", "B♭m7", "D♭", "E♭m", "A♭m7", "B♭m7", "D♭", "G♭", "E♭m", "A♭m7", "B♭m7", "D♭", "E♭m", "A♭m7", "B♭m7", "D♭", "G♭", "E♭m", "A♭m7", "B♭m7", "D♭", "E♭m", "A♭m7", "B♭m7", "D♭", "G♭", "E♭m", "A♭m7", "D♭", "G♭", "B", "E", "F", "G♭", "G", "A♭", "A", "B♭7", "N.C", "E♭m", "E♭m", "Cm7-5", "B", "B♭7", "D♭", "E♭m", "Cm7-5", "B", "B♭7", "D♭", "E♭m", "E♭m", "Cm7-5", "B", "B♭7", "D♭", "E♭m", "Cm7-5", "B", "B♭7", "D♭", "E♭m", "N.C"]}