{"id": 25487, "song": "summer tail", "artist": "KEYTALK", "composer": "寺中友将", "chord": ["C", "C", "Em", "Em7-5", "A", "Dm", "D♭aug", "F", "Gsus4", "G", "C", "Em", "Em7-5", "A", "Dm", "D♭aug", "F", "Gsus4", "G", "C", "C7", "Am", "D7", "F", "G", "C", "C7", "Am", "D7", "Fm", "B♭", "E♭", "G", "Cm", "E♭", "B♭m7", "E♭", "A♭", "B♭", "G", "Cm", "Fm", "B♭", "E♭", "A♭", "E♭", "A♭", "C", "Em", "Em7-5", "A", "Dm", "D♭aug", "F", "Gsus4", "G", "C", "Em", "Em7-5", "A", "Dm", "D♭aug", "F", "Gsus4", "G", "C", "C7", "Am", "D7", "F", "G", "C", "C7", "Am", "D7", "Fm", "B♭", "E♭", "G", "Cm", "E♭", "B♭m7", "E♭", "A♭", "B♭", "G", "Cm", "Fm", "A♭m", "D♭", "E♭", "G", "Cm", "E♭", "B♭m7", "E♭", "A♭", "B♭", "G", "Cm", "Fm", "B♭", "Cm", "A♭", "B♭", "Cm", "A♭", "B♭", "E♭", "Cm", "A♭", "B♭", "Cm", "A♭", "B♭", "A♭", "E♭", "G", "Cm", "E♭", "B♭m7", "E♭", "A♭", "B♭", "G", "Cm", "Fm", "B♭", "E♭sus4", "E♭"]}