{"id": 4142, "song": "志 -kokorozashi-", "artist": "UVERworld", "composer": "Reigo5", "chord": ["A", "F#m", "G", "D", "Bm", "A", "G", "D", "Bm", "F#m", "G", "D", "Bm", "A", "G", "D", "Bm", "D", "G", "F#m", "Bm", "A", "G", "D", "Bm", "D", "Bm", "A", "G", "D", "Bm", "F#m", "G", "F#m", "Bm", "A", "G", "D", "Bm", "F#m", "G", "A", "Bm", "A", "G", "D", "Bm", "F#m", "G", "F#m", "Bm", "A", "G", "D", "Bm", "F#m", "G", "A", "Bm", "A", "G", "D", "Bm", "F#m", "G", "F#m", "Bm", "A", "G", "D", "Bm", "F#m", "G", "A", "Bm", "A", "G", "D", "Bm", "F#m", "G", "F#m", "Bm", "A", "G", "D", "Bm", "D", "G", "F#m", "Bm", "A", "G", "D", "Bm", "D", "Bm", "A", "G", "D", "Bm", "F#m", "G", "A", "Bm", "A", "G", "D", "Bm", "F#m", "G", "A", "Bm", "A", "G", "D", "Bm", "F#m", "G", "A", "Bm", "A", "G", "D", "Bm", "F#m", "G", "A", "Bm", "A", "G", "D", "Bm", "F#m", "G", "A", "Bm", "A", "G", "D", "Bm", "F#m", "G", "F#m", "Bm", "A", "G", "D", "Bm", "D", "G", "F#m", "Bm", "A", "G", "D", "Bm", "D", "Bm", "A", "G", "D", "Bm", "F#m", "G", "A", "Bm", "A", "G", "D", "Bm", "F#m", "G", "A", "Bm", "A", "G", "D", "Bm", "A", "G", "F#m", "Bm", "A", "G", "D", "Bm", "D"]}