{"id": 10173, "song": "緑の日々", "artist": "小田和正", "composer": "小田和正", "chord": ["A", "F#m7", "D", "E7sus4", "E7", "A", "F#m7", "D", "E7sus4", "E7", "Am7", "Dm7", "Am7", "Dm7", "Am7", "Dm7", "Bm7-5", "E7sus4", "E7", "Am7", "Dm7", "Gsus4", "Cmaj7", "Am7", "Dm7", "Bm7-5", "E7sus4", "E7", "Fmaj7", "Em7", "Dm7", "Am7", "Dm7", "Bm7-5", "E7sus4", "E7", "Am7", "Dm7", "Gsus4", "Cmaj7", "Am7", "Dm7", "Bm7-5", "E7sus4", "E7", "Fmaj7", "Em7", "Dm7", "A", "F#m7", "Dmaj7", "E7sus4", "E7", "A", "F#m7", "Dmaj7", "E7sus4", "E7", "Am7", "Dm7", "Bm7-5", "E7sus4", "E7", "Am7", "Dm7", "Gsus4", "Cmaj7", "Am7", "Dm7", "Bm7-5", "E7sus4", "E7", "Fmaj7", "Em7", "Dm7", "A", "F#m7", "Dmaj7", "E7sus4", "E7", "A", "F#m7", "Dmaj7", "Dm7", "Am7", "Dm7", "Dm7", "G", "G", "Cmaj7", "Am7", "Dm7", "Fmaj7", "Em7", "Dm7", "Fmaj7", "Em7", "Dm7", "A", "F#m7", "Dmaj7", "E7sus4", "E7", "A", "F#m7", "Dmaj7", "E7sus4", "E7", "B", "G#m7", "E", "F#7sus4", "F#7", "B", "G#m7", "E", "F#7sus4", "F#7", "B", "G#m7", "E", "F#7sus4", "F#7", "B", "G#m7", "E", "F#7sus4", "F#7", "B", "G#m7", "E", "F#7sus4", "F#7", "B", "G#m7", "E", "F#7sus4", "F#7"]}