{"id": 20843, "song": "眉", "artist": "村下孝蔵", "composer": "村下孝蔵", "chord": ["N.C.", "Em", "C", "D", "G", "Em", "C", "D", "N.C.", "Em", "C", "Em", "C", "D", "D#dim", "Em", "C", "Am", "B", "C", "B", "Em", "F#dim", "G", "F#dim", "B7", "Em", "D", "G", "Em", "Am7", "B7", "Em", "Em", "D", "G", "Em", "C", "B7", "Em", "C", "D", "G", "Em", "C", "D", "N.C.", "Em", "C", "Em", "C", "D", "D#dim", "Em", "C", "Am", "B", "C", "B", "Em", "F#dim", "G", "F#dim", "B7", "Em", "D", "G", "Em", "Am7", "B7", "Em", "Em", "D", "G", "Em", "C", "B7", "C7sus4", "C7", "Fm", "D♭", "Fm", "D♭", "Fm", "D♭", "E♭", "Fsus4", "F", "N.C.", "Fm", "D♭", "E♭", "A♭", "Fm", "D♭", "E♭", "N.C.", "Fm"]}