{"id": 13479, "song": "終電マスター", "artist": "FREENOTE", "composer": "MASAYA SAKAMOTO", "chord": ["A", "G", "D", "C", "A", "G", "D", "C", "A", "G", "D", "C", "A", "G", "D", "C", "A", "D", "A", "D", "C#m", "D", "C#m", "D", "A", "D", "A", "D", "C#m", "D", "C#m", "D", "Bm", "C#m", "D", "C#m", "Bm", "C#m", "D", "E", "F#m", "C#m", "D", "E", "F#m", "C#m", "D", "E", "F#m", "C#m", "D", "F", "A", "G", "D", "C", "A", "G", "D", "C", "A", "G", "D", "C", "A", "G", "D", "C", "A", "D", "A", "D", "C#m", "D", "C#m", "D", "A", "D", "C#m", "D", "A", "D", "C#m", "D", "A", "D", "C#m", "D", "A", "D", "C#m", "Cm", "Bm", "D", "E", "F#m", "C#m", "D", "E", "F#m", "D", "E", "F#m", "C#m", "D", "E", "F#m", "C#m", "D", "E", "F#m", "C#m", "D", "E", "F", "F", "G", "A", "G", "D", "C", "A", "G", "D", "C", "A", "G", "D", "C", "A", "G", "D", "C", "A", "G", "D", "C", "A", "G", "D", "C", "A", "G", "D", "C", "A", "G", "D", "C", "D", "C", "D"]}