{"id": 13451, "song": "変態", "artist": "Syrup 16g", "composer": "五十嵐隆", "chord": ["E♭m", "D♭", "E♭m", "D♭", "E♭m", "D♭", "E♭m", "D♭", "E♭m", "B♭m", "B", "A♭m", "E♭m", "B♭m", "B", "A♭m", "E♭m", "B♭m", "B", "A♭m", "E♭m", "B♭m", "B", "A♭m", "E♭m", "B♭m", "B", "D♭", "E♭m", "D♭", "E♭m", "B♭m", "B", "A♭m", "E♭m", "B♭m", "B", "A♭m", "E♭m", "B♭m", "B", "D♭", "E♭m", "E", "G#m", "C#m", "C#m7", "A", "E", "G#m", "C#m", "C#m7", "A", "E♭m", "D♭", "E♭m", "D♭", "E♭m", "D♭", "E♭m", "D♭", "E♭m", "B♭m", "B", "A♭m", "E♭m", "B♭m", "B", "A♭m", "E♭m", "B♭m", "B", "A♭m", "E♭m", "B♭m", "B", "A♭m", "E♭m", "B♭m", "B", "A♭m", "E♭m", "B♭m", "B", "D♭", "E♭m", "E", "G#m", "C#m", "C#m7", "A", "E", "G#m", "C#m", "C#m7", "A", "E", "G#m", "C#m", "C#m7", "A", "E", "G#m", "C#m", "C#m7", "A", "E♭m", "D♭", "E♭m", "D♭", "E♭m", "D♭", "E♭m", "D♭", "E♭m", "D♭", "E♭m", "D♭", "E♭m", "D♭", "E♭m", "D♭", "E♭m"]}