{"id": 653, "song": "Hey！Mr. Angryman", "artist": "斉藤和義", "composer": "斉藤和義", "chord": ["E", "B", "C#m", "E7", "A", "Am", "E", "B7", "E", "B", "C#m", "E7", "A", "Am", "E", "G#m", "C#m", "A", "Am", "E", "Esus4", "E", "G#m", "C#m", "F#m", "D7", "B7", "E", "B", "C#m", "E7", "A", "Am", "E", "B7", "E", "B", "C#m", "E7", "A", "Am", "E7", "A7", "E7", "A7", "E7", "A7", "E7", "A7", "E7", "A7", "E7", "A7", "E7", "A7", "E7", "G#m", "C#m", "A", "Am", "E", "Esus4", "E", "G#m", "C#m", "F#m", "D7", "B7", "E", "B", "C#m", "E7", "A", "Am", "E", "B7", "E", "B", "C#m", "E7", "A", "Am", "E", "B", "C#m", "E7", "A", "Am", "E", "B7", "E", "B", "C#m", "E7", "A", "Am", "E", "B", "C#m", "G#m", "A", "E", "F#m", "B"]}