{"id": 74826, "song": "風が吹く", "artist": "S.O.S!～sound of smile!～", "composer": "YUI", "chord": ["E♭maj7", "F", "Gm7", "Dm7", "G♭dim", "Gm7", "Cm7", "F", "E♭m", "E♭m", "F", "F7", "B♭", "E♭maj7", "F", "Gm7", "Dm7", "G♭dim", "Gm7", "Cm7", "F", "E♭m", "E♭m", "F", "F7", "B♭", "B♭", "E♭maj7", "F", "B♭", "Gm7", "E♭maj7", "F", "B♭", "B♭", "Cm7", "Dm7", "F", "Gm7", "Gm7", "Dm7", "E♭maj7", "E♭m", "F", "F7", "B♭", "E♭maj7", "F", "Gm7", "B♭", "E♭maj7", "F", "Gm7", "B♭", "E♭maj7", "F", "Gm7", "B♭", "Cm7-5", "E♭m", "F", "B♭", "F", "E♭maj7", "B♭", "F", "A", "Gm7", "E♭maj7", "F", "B♭", "B♭", "F", "E♭maj7", "B♭", "F", "A", "Gm7", "E♭maj7", "F", "B♭", "Gm7", "E♭maj7", "F", "B♭", "E♭maj7", "F", "Gm7", "Dm7", "G♭dim", "Gm7", "Cm7", "F", "E♭m", "E♭m", "F", "F7", "B♭", "B♭", "E♭", "B♭", "F", "B♭", "B♭", "B♭", "E♭", "B♭", "F", "B♭", "B♭", "B♭", "Cm7", "Dm7", "F", "Gm7", "Gm7", "Dm7", "E♭maj7", "E♭m", "F", "F7", "B♭", "E♭maj7", "F", "Gm7", "B♭", "E♭maj7", "F", "Gm7", "B♭", "E♭maj7", "F", "Gm7", "B♭", "Cm7-5", "E♭m", "F", "B♭", "F", "E♭maj7", "B♭", "F", "A", "Gm7", "E♭maj7", "F", "B♭", "B♭", "F", "E♭maj7", "B♭", "F", "A", "Gm7", "E♭maj7", "F", "B♭", "Gm7", "E♭maj7", "F", "B♭", "B♭", "E♭", "B♭", "F", "B♭", "E♭maj7", "F", "Gm7", "B♭", "E♭maj7", "F", "Gm7", "B♭", "E♭maj7", "F", "Gm7", "B♭", "E♭maj7", "F", "Gm7", "B♭", "E♭maj7", "F", "Gm7", "B♭", "E♭maj7", "F", "Gm7", "B♭", "E♭maj7", "F", "Gm7", "B♭", "E♭maj7", "F", "Gm7", "B♭", "E♭maj7", "F", "Gm7", "B♭", "E♭maj7", "F", "Gm7", "B♭", "E♭maj7", "F", "G♭dim", "Gm7", "C", "Cm7", "F", "B♭", "E♭maj7", "F", "Gm7", "B♭", "Cm7", "F", "B♭", "E♭maj7", "F", "G♭dim", "Gm7", "C", "Cm7", "F", "B♭", "E♭maj7", "F", "Gm7", "B♭", "Cm7", "F", "Gm7", "B♭", "E♭maj7", "F", "G♭dim", "Gm7", "C", "Cm7", "F", "B♭"]}