{"id": 62928, "song": "drama", "artist": "AAA", "composer": "SiZK・MUSOH", "chord": ["F#", "C#", "F", "D#m", "B", "F#", "C#", "F", "D#m", "B", "F#", "C#", "F", "D#m", "B", "C#", "F#", "C#", "F", "D#m", "B", "C#", "F#", "C#", "F", "D#m", "B", "C#", "F#", "C#", "F", "D#m", "B", "C#", "G#m", "A#m", "B", "A#m", "G#m", "A#m", "B", "F#", "C#", "F", "D#m", "B", "C#", "F#", "C#", "F", "D#m", "B", "C#", "F#", "C#", "F", "D#m", "B", "C#", "F#", "C#", "F", "D#m", "B", "C#", "F#", "C#", "F", "D#m", "B", "C#", "F#", "C#", "F", "D#m", "B", "C#", "F#", "C#", "F", "D#m", "B", "F#", "C#", "F", "D#m", "B", "F#", "C#", "F", "D#m", "B", "C#", "F#", "C#", "F", "D#m", "B", "C#", "G#m", "A#m", "B", "A#m", "G#m", "A#m", "B", "F#", "C#", "F", "D#m", "B", "C#", "F#", "C#", "F", "D#m", "B", "C#", "F#", "C#", "F", "D#m", "B", "C#", "F#", "C#", "F", "D#m", "B", "C#", "D#m", "B", "C#", "F#", "C#", "F", "D#m", "B", "C#", "F#", "C#", "F", "D#m", "B", "C#", "G#", "C#", "F", "D#m", "B", "C#", "F#", "C#", "F", "D#m", "B", "C#", "F#", "C#", "F", "D#m", "D#m", "B", "C#", "F#", "C#", "F", "D#m", "B", "C#", "F#", "C#", "F", "D#m", "B", "C#", "F#", "C#", "F", "D#m", "B", "C#", "F#", "C#", "F", "D#m", "B", "C#", "F#", "C#", "F", "D#m", "B", "C#", "F#", "C#", "F", "D#m", "B", "C#", "F#", "C#", "F", "D#m", "B", "C#", "F#", "C#", "F", "D#m", "B", "C#", "F#", "C#", "F", "D#m", "B", "C#", "F#", "C#", "F", "D#m", "B", "C#", "F#", "C#", "F", "D#m", "B", "C#", "F#", "C#", "F", "D#m", "B", "C#", "F#", "C#", "F", "D#m", "B", "C#", "F#", "C#", "F", "D#m", "B", "C#"]}