{"id": 43923, "song": "Cry", "artist": "清木場俊介", "composer": "清木場俊介・川根来音", "chord": ["Em", "Em", "C", "D", "Em", "C", "D", "Em", "Em", "C", "D", "Em", "C", "D", "Em", "C", "D", "Em", "C", "D", "Em", "Em", "C", "D", "Em", "Em", "C", "D", "Em", "C", "D", "Em", "C", "D", "Em", "Em", "C", "D", "Em", "C", "D", "Em", "Em", "C", "D", "Em", "C", "D", "Em", "C", "D", "Em", "C", "D", "Em", "Em", "C", "D", "Em", "Em", "C", "D", "Em", "C", "D", "Em", "Em", "C", "D", "Em", "C", "D", "Em", "C", "D", "Em", "C", "D", "Em", "C", "D", "Em", "C", "D", "Em"]}