{"id": 27618, "song": "海の声", "artist": "BEGIN", "composer": "島袋優", "chord": ["E♭", "Fm", "E♭", "G", "A♭", "E♭", "Fm", "E♭", "G", "A♭", "B♭sus4", "B♭", "E♭", "B♭", "A♭", "E♭", "B♭", "D", "Cm", "Gm", "Fm", "B♭", "E♭", "B♭", "A♭", "E♭", "B♭", "D", "Cm", "Gm", "A♭m", "E♭", "Fm", "E♭", "G", "A♭", "E♭", "Fm", "E♭", "G", "A♭", "E♭", "Fm", "E♭", "G", "A♭", "E♭", "Fm", "E♭", "G", "A♭", "Gm7", "Cm", "Fm", "B♭sus4", "B♭", "G", "A♭", "B♭", "Gm", "Cm", "A♭", "B♭", "E♭", "G", "A♭", "B♭", "Gm", "Cm", "Fm", "B♭sus4", "B♭", "B♭sus4", "B♭", "B♭sus4", "B♭", "E♭", "B♭", "A♭", "E♭", "B♭", "D", "Cm", "Gm", "Fm", "B♭", "E♭", "B♭", "A♭", "E♭", "B♭", "D", "Cm", "Gm", "A♭m", "E♭", "B♭", "A♭", "E♭", "B♭", "D", "Cm", "Gm", "Fm", "B♭", "E♭", "B♭", "A♭", "E♭", "B♭", "D", "Cm", "Gm", "A♭m", "E♭", "G", "A♭", "B♭", "Gm", "Cm", "A♭", "B♭", "E♭", "G", "A♭", "B♭", "Gm", "Cm", "Fm", "B♭sus4", "B♭", "B♭sus4", "B♭", "B♭sus4", "E♭", "B♭", "A♭", "E♭", "B♭", "D", "Cm", "Gm", "Fm", "B♭", "E♭", "B♭", "A♭", "E♭", "B♭", "D", "Cm", "Gm", "A♭m", "E♭", "E♭", "B♭", "A♭", "E♭", "B♭", "D", "Cm", "Gm", "A♭m", "E♭", "Fm", "E♭", "G", "A♭", "E♭", "Fm", "E♭", "G", "A♭", "E♭"]}