{"id": 58600, "song": "Twilight", "artist": "藤原さくら", "composer": "藤原さくら", "chord": ["A", "C#m", "D", "E", "A", "C#m", "D", "E", "A", "C#m", "D", "E", "A", "C#m", "D", "E", "A", "C#m", "D", "E", "F#m", "C#m", "D", "E", "A", "C#m", "D", "E", "F#m", "C#m", "D", "E", "A", "D", "E", "F#m", "C#m", "D", "E", "F#m", "C#m", "D", "E", "F#m", "C#m", "D", "E", "A", "A", "C#m", "D", "E", "A", "C#m", "D", "E", "A", "C#m", "D", "E", "F#m", "C#m", "D", "E", "A", "C#m", "D", "E", "F#m", "C#m", "D", "E", "A", "D", "E", "F#m", "C#m", "D", "E", "F#m", "C#m", "D", "E", "F#m", "C#m", "D", "E", "A", "A", "C#m", "D", "E", "A", "C#m", "D", "E", "A", "C#m", "D", "E", "F#m", "C#m", "D", "E", "A", "A", "C#m", "D", "E", "A", "C#m", "D", "E", "A", "C#m", "D", "E", "F#m", "C#m", "D", "E", "A", "D", "E", "F#m", "C#m", "D", "A", "D", "E", "F#m", "C#m", "D", "N.C", "A", "C#m", "D", "E", "A", "C#m", "D", "E", "A", "C#m", "D", "E", "F#m", "C#m", "D", "E", "A", "A", "C#m", "D", "E", "A", "C#m", "D", "E", "D", "D#dim", "E", "Fdim", "F#m", "C#m", "D", "E", "A", "N.C", "A", "C#m", "D", "E", "A", "C#m", "D", "E", "A"]}