{"id": 80927, "song": "蛍星", "artist": "元ちとせ", "composer": "常田真太郎", "chord": ["E♭", "Dm", "Cm", "F", "E♭", "Dm", "D♭", "Cm", "F", "B♭", "F", "A", "Gm", "Dm", "E♭", "Dm", "Cm", "F7+5", "F7", "B♭", "F", "A", "Gm", "Dm", "A♭dim", "Cm", "E♭m", "B♭", "B♭", "F", "A", "Gm", "Dm", "E♭", "Dm", "Cm", "F7+5", "F7", "B♭", "F", "A", "Gm", "Dm", "A♭dim", "Cm", "E♭m", "B♭", "B♭", "E♭", "Dm", "Cm", "F", "E♭", "Dm", "A♭dim", "Cm", "F", "D", "F#", "G", "Bm", "C", "D", "Em", "Bm", "Am", "D", "G", "Bm", "C", "D", "B", "D#", "Em", "Bm", "C", "D", "D", "C", "Bm", "E7-9", "Am", "Am7", "D", "E♭", "E♭", "B♭", "E♭", "Dm", "B♭", "B♭", "F", "A", "Gm", "Dm", "E♭", "Dm", "Cm", "F7+5", "F7", "B♭", "F", "A", "Gm", "Dm", "A♭dim", "Cm", "E♭m", "B♭", "B♭", "E♭", "Dm", "Cm", "F", "E♭", "Dm", "A♭dim", "Cm", "F", "D", "F#", "G", "Bm", "C", "D", "Em", "Bm", "Am", "D", "G", "Bm", "C", "D", "B", "D#", "Em", "Bm", "C", "D", "D", "C", "Bm", "E7-9", "Am", "Am7", "D", "Bm", "Bm", "C", "C", "D", "C", "D", "Bm", "C", "D", "D", "G", "Bm", "C", "D", "Em", "Bm", "Am", "D", "G", "Bm", "C", "D", "B", "D#", "Em", "Bm", "C", "D", "G", "Bm", "C", "D", "Em", "Bm", "Am", "D", "G", "Bm", "C", "D", "B", "D#", "Em", "Bm", "C", "D", "D", "C", "Bm", "E7-9", "Am", "Am7", "D", "C", "Bm", "Am", "D", "C", "Bm", "B♭", "Am", "D", "G"]}