{"id": 55153, "song": "BOYS GO CRAZY", "artist": "THE MODS", "composer": "森山達也", "chord": ["B", "A", "E", "E", "B", "A", "E", "A", "E", "A", "B", "A", "E", "A", "B", "A", "E", "A", "B", "E", "E", "A", "E", "B", "A", "E", "A", "E", "B", "A", "E", "B", "A", "E", "E", "B", "A", "E", "A", "E", "A", "B", "A", "E", "A", "B", "A", "E", "A", "B", "E", "A", "E", "A", "E", "A", "B", "A", "E", "A", "E", "A", "E", "A", "B", "G", "A", "E", "A", "E", "A", "E", "A", "E", "A", "E", "A", "E", "A", "B", "E", "E7"]}