{"id": 25877, "song": "On Your Side", "artist": "Superfly", "composer": "Bonnie Mckee・Michelle McCord", "chord": ["A♭", "C", "D♭", "E♭", "Fm", "A♭", "C", "D♭", "E♭", "A♭", "E♭", "G", "Fm", "A♭", "E♭", "A♭", "E♭", "G", "E", "G♭", "A♭", "B♭m7", "E♭", "A♭", "E♭", "G", "Fm", "E♭", "B♭7", "E♭", "A♭", "E♭", "Fm", "D♭", "A♭", "E♭", "Fm", "E♭", "D♭", "A♭", "E♭", "D♭", "D♭m", "A♭", "E♭", "G", "Fm", "A♭", "E♭", "A♭", "E♭", "G", "E", "G♭", "A♭", "B♭m7", "E♭", "A♭", "E♭", "G", "Fm", "E♭", "B♭7", "E♭", "A♭", "E♭", "Fm", "D♭", "A♭", "E♭", "Fm", "E♭", "D♭", "A♭", "E♭", "D♭", "E", "G♭", "A♭", "C", "D♭", "E♭", "Fm", "A♭", "C", "D♭", "E♭", "Fm", "Eaug", "A♭", "E♭", "B♭", "D", "D♭", "E♭", "Fm", "E♭", "D♭", "E♭", "F", "E", "A", "E", "F#m", "D", "A", "E", "Fm", "D", "E", "A", "E", "F", "G", "A", "F", "G", "A", "F", "G", "A", "A", "C#", "D", "E", "F#m", "A", "C#", "D", "E", "F#m", "A", "C#", "D", "E", "F#m", "A", "C#", "D", "E", "F#m", "A", "C#", "D", "E", "F#m", "A", "C#", "D", "E", "F#m", "A", "C#", "D", "E", "F#m", "A", "C#", "D", "E", "F#m"]}