{"id": 58271, "song": "愛別れ", "artist": "ほのかりん", "composer": "ほのかりん", "chord": ["D", "F#", "Gmaj7", "Bsus4", "B", "Bm", "E9", "Gmaj7", "Bsus4", "B", "Em7", "Asus4", "A", "D", "F#", "Bm", "E9", "Gmaj7", "A", "F#", "Bm", "A", "D", "F#", "Bm", "E9", "Gmaj7", "A", "Gmaj7", "F#m7", "Em7", "D", "Cmaj7", "Asus4", "A", "D", "F#", "Gmaj7", "Bsus4", "B", "Bm", "E9", "Gmaj7", "Bsus4", "B", "Em7", "Asus4", "A", "D", "F#", "Bm", "E9", "Gmaj7", "A", "F#", "Bm", "A", "D", "F#", "Bm", "E9", "Gmaj7", "A", "Bm", "E9", "Bm7", "E", "Bm7", "E", "Gmaj7", "A", "D", "F#", "Bm", "E9", "Gmaj7", "A", "F#", "Bm", "A", "D", "F#", "Bm", "E9", "Gmaj7", "A", "Bm", "E9", "Bm7", "E", "Bm7", "E", "Gmaj7", "A", "N.C.", "Gmaj7"]}