{"id": 87625, "song": "遊郭跡地", "artist": "亜沙", "composer": "亜沙", "chord": ["N.C.", "D♭add9", "D♭", "A♭sus4", "B♭m7", "G♭add9", "D♭add9", "A♭sus4", "B♭m7", "G♭add9", "D♭add9", "A♭sus4", "B♭m7", "G♭add9", "G♭", "A♭", "B♭m7", "A♭", "G♭", "A♭", "B♭m7", "A♭", "D♭add9", "D♭add9", "A♭sus4", "B♭m7", "G♭add9", "D♭add9", "N.C.", "D♭add9", "N.C.", "A♭sus4", "B♭m7", "G♭add9", "G♭", "A♭", "B♭m7", "A♭", "G♭", "A♭", "B♭m7", "A♭", "G♭", "A♭", "B♭m7", "A♭", "G♭", "A♭", "B♭m7", "A♭", "G♭", "A♭", "B♭m7", "A♭", "G♭", "A♭", "B♭m7", "A♭", "G♭", "A♭", "B♭m7", "A♭", "G♭", "A♭", "B♭m7", "A♭", "B♭m7", "A♭", "G♭", "A♭", "B♭m7", "A♭", "G♭", "A♭", "G♭", "A♭", "B♭m7", "D♭add9", "G♭", "A♭", "D♭add9"]}