{"id": 74634, "song": "NO WAY", "artist": "m-flo", "composer": "VERBAL/TAKU", "chord": ["Fm", "Fm", "Fm", "Fm", "Fm", "Fm", "Fm", "Fm", "Fm", "Fm", "D♭", "E♭", "D♭", "E♭", "Fm", "D♭", "E♭", "D♭", "E♭", "Fm", "D♭", "E♭", "D♭", "D♭", "E♭", "Fm", "D♭", "E♭", "D♭", "D♭", "E♭", "Fm", "Fm", "Fm", "N.C.", "N.C.", "N.C.", "N.C.", "N.C.", "N.C.", "N.C.", "N.C.", "N.C.", "N.C.", "N.C.", "Fm", "Fm", "Fm", "Fm", "D♭", "E♭", "D♭", "E♭", "Fm", "D♭", "E♭", "D♭", "E♭", "Fm", "D♭", "E♭", "D♭", "D♭", "E♭", "Fm", "D♭", "E♭", "D♭", "D♭", "E♭", "Fm", "Fm", "Fm"]}