{"id": 68110, "song": "鈍色の夜明け", "artist": "三浦祐太朗", "composer": "佐々倉有吾", "chord": ["D♭", "E♭", "Fm", "Cm", "D♭", "E♭", "Fm", "Cm", "D♭", "E♭", "C7", "Fm", "Cm", "D♭", "B♭m", "C7", "D♭", "E♭", "Fm", "D♭", "E♭", "C7", "Fm", "D♭", "E♭", "G♭", "F7", "D♭", "E♭", "Edim", "Fm", "D♭", "E♭", "Fm", "FmM7", "Fm7", "Dm7-5", "D♭", "E♭", "C7", "Fm", "D♭", "E♭", "Fm", "Cm", "D♭", "B♭m", "Cm", "Fm", "Cm", "D♭", "B♭m", "Cm", "D♭", "E♭", "Fm", "D♭", "E♭", "C7", "Fm", "D♭", "E♭", "G♭", "F7", "D♭", "E♭", "Edim", "Fm", "D♭", "E♭", "Fm", "FmM7", "Fm7", "Dm7-5", "D♭", "E♭", "C7", "Fm", "Fm", "E♭", "Cm", "D♭", "Fm", "E♭", "Cm", "D♭", "B♭m", "Cm", "C7", "Fm", "D♭", "E♭", "G♭", "F7", "D♭", "E♭", "Edim", "Fm", "D♭", "E♭", "Fm", "FmM7", "Fm7", "Dm7-5", "D♭", "E♭", "C7", "Fm"]}