{"id": 68763, "song": "AGAINST THE WALL", "artist": "ストレイテナー", "composer": "ホリエアツシ", "chord": ["D♭", "Fm7", "E♭", "A♭", "D♭", "Fm7", "E♭", "A♭", "D♭", "Fm7", "E♭", "A♭", "A♭", "D♭", "E♭", "Fm7", "A♭", "D♭", "E♭", "Fm7", "A♭", "D♭", "E♭", "Fm7", "A♭", "D♭", "E♭", "Fm7", "A♭", "D♭", "Fm7", "E♭", "A♭", "D♭", "Fm7", "E♭", "A♭", "A♭", "D♭", "E♭", "Fm7", "A♭", "D♭", "E♭", "Fm7", "A♭", "D♭", "E♭", "Fm7", "A♭", "D♭", "E♭", "Fm7", "A♭", "D♭", "Fm7", "E♭", "A♭", "D♭", "Fm7", "E♭", "A♭", "B♭m", "Fm7", "E♭", "G", "A♭", "B♭m", "Fm7", "E♭", "G", "A♭", "B♭m", "Fm7", "E♭", "G", "A♭", "B♭m", "Fm7", "E♭", "G", "A♭", "B♭m", "Fm7", "E♭", "G", "A♭", "B♭m", "Fm7", "E♭", "G", "A♭", "A♭", "D♭", "E♭", "Fm7", "A♭", "D♭", "E♭", "Fm7", "A♭", "D♭", "E♭", "Fm7", "A♭", "D♭", "D♭", "E♭", "Fm7", "A♭", "D♭", "Fm7", "E♭", "A♭", "D♭", "Fm7", "E♭", "A♭"]}