{"id": 24024, "song": "桜花爛漫", "artist": "KEYTALK", "composer": "首藤義勝", "chord": ["B♭", "Cadd9", "F", "A", "Dm", "Dm7", "B♭", "A", "B♭", "Cadd9", "Am", "Dm7", "F7", "B♭", "A", "B♭", "C", "Dm", "Gm", "C", "F", "B♭", "C", "Am", "Dm", "Gm", "C", "F", "Am", "Dm", "Gm", "C", "Am", "Dm", "Gm7", "A7", "B♭", "Cadd9", "F", "Dm", "B♭", "Cadd9", "F", "A", "Dm", "C", "B♭", "Cadd9", "F", "A", "Dm7", "F7", "B♭", "A", "Dm7", "B♭", "Cadd9", "Am", "Dm7", "F7", "B♭", "A", "B♭", "C", "Dm", "Gm", "C", "F", "B♭", "C", "Am", "Dm", "Gm", "C", "F", "Am", "Dm", "Gm", "C", "Am", "Dm", "Gm7", "A7", "B♭", "Cadd9", "F", "Dm", "B♭", "Cadd9", "F", "A", "Dm", "C", "B♭", "Cadd9", "F", "A", "Dm7", "F7", "B♭", "A", "A♭", "B♭", "E♭", "G7", "Cm", "B♭", "Fm", "B♭", "Bdim", "Cm", "Fm", "G", "A♭", "B♭", "E♭", "Cm", "A♭", "B♭", "C", "Dm", "B♭", "Cadd9", "F", "Dm", "B♭", "Cadd9", "F", "A", "Dm", "C", "B♭", "Cadd9", "F", "A", "Dm7", "F7", "B♭", "Cadd9", "Dm", "B♭", "A", "Dm7", "C", "Dm", "B♭", "Cadd9", "Am", "Dm7", "F7", "B♭", "A", "Dm"]}