{"id": 94018, "song": "さよなら", "artist": "吉野裕行", "composer": "宮崎誠", "chord": ["C", "F", "G", "Fm", "G", "C", "Fm", "C", "C", "Am", "G", "Dm", "F", "Em", "F", "G", "C", "Bdim", "E", "Am", "G", "F#dim", "D", "F", "G", "C", "G", "B", "Am", "G", "Dm", "Gsus4", "C", "F", "C", "G", "Am", "F", "C", "E", "G#dim", "Am", "Em", "Fm", "G", "C", "F", "G", "E", "Am", "C", "G", "F", "C", "F#dim", "G", "C", "F", "G", "E", "Am", "C", "G", "F", "C", "G", "Am", "Dm", "G", "C", "F", "G", "Fm", "G", "G", "C", "Bdim", "E", "Am", "G", "F#dim", "D", "F", "G", "C", "G", "B", "Am", "G", "Dm", "Gsus4", "C", "F", "C", "G", "Am", "F", "C", "E", "G#dim", "Am", "Em", "Fm", "G", "C", "F", "G", "E", "Am", "C", "G", "F", "C", "F#dim", "G", "C", "F", "G", "E", "Am", "G", "F", "C", "G", "Am", "Dm", "Gsus4", "F", "G", "E", "G#dim", "Am", "C", "G", "Dm", "D", "F#", "Gsus4", "E", "Am", "G", "F", "C", "Am", "G", "F", "G", "C", "F", "G", "E", "Am", "C", "G", "F", "C", "F#dim", "G", "C", "F", "G", "E", "Am", "G", "F", "C", "G", "Am", "Dm", "G", "C", "F", "G", "G", "C"]}