{"id": 3073, "song": "シクラメンのかほり", "artist": "布施明", "composer": "小椋佳", "chord": ["Gm", "Cm", "D", "Cm", "Gm", "F", "Gm", "Gm", "Cm", "Gm", "D", "Cm", "Gm", "F", "Gm", "F", "E♭", "D7", "Cm", "Gm", "D", "Gm", "Gm", "Cm", "Gm", "D", "Cm", "Gm", "F", "Gm", "F", "E♭", "D7", "Cm", "Gm", "D", "Gm", "Cm", "Gm", "Cm", "Gm", "Cm", "Gm", "Cm", "Dsus4", "D", "Gm", "Cm", "Gm", "D7", "Gm", "Cm", "E♭", "D7", "Gm", "Cm", "Gm", "D", "Cm", "Gm", "F", "Gm", "F", "E♭", "D7", "Cm", "Gm", "D", "Gm", "Cm", "Gm", "Cm", "Gm", "Cm", "Gm", "Cm", "Dsus4", "D", "Cm", "Gm", "F", "Gm"]}