{"id": 92405, "song": "ブラックペッパーのたっぷりきいた私の作ったオニオンスライス", "artist": "上白石萌音", "composer": "根本要", "chord": ["A♭6", "F7", "B♭7", "E♭7", "A♭6", "F7", "B♭7", "E♭7", "A♭6", "B♭m7", "Bdim", "A♭", "C", "D♭7", "A♭6", "F7", "B♭7", "E♭7", "B", "B♭", "A", "A♭6", "N.C.", "E♭aug", "A♭6", "E♭aug", "A♭6", "Gm7", "C7", "Fm7", "B♭7", "D♭6", "D♭", "E♭", "A♭6", "E♭aug", "A♭6", "Gm7", "C7", "Fm7", "B♭7", "D♭6", "D♭", "E♭", "A♭6", "E♭7", "A♭6", "F7", "B♭7", "E♭7", "A♭6", "F7", "B♭7", "E♭7", "A♭6", "B♭m7", "Bdim", "A♭", "C", "D♭7", "A♭6", "F7", "B♭7", "E♭7", "B", "B♭", "A", "A♭6", "N.C.", "E♭aug", "A♭6", "E♭aug", "A♭6", "Gm7", "C7", "Fm7", "B♭7", "D♭6", "D♭", "E♭", "A♭6", "E♭aug", "A♭6", "Gm7", "C7", "Fm7", "B♭7", "D♭6", "D♭", "E♭", "A♭6", "E♭7", "A♭6", "F7", "B♭7", "E♭7", "A♭6", "F7", "B♭7", "E♭7", "A♭6", "B♭m7", "Bdim", "A♭", "C", "D♭7", "A♭6", "F7", "B♭7", "E♭7", "B", "B♭", "A", "A♭6", "A♭6", "F7", "B♭7", "E♭7", "A♭6", "F7", "B♭7", "E♭7", "A♭6", "F7", "B♭7", "E♭7", "A♭6", "F7", "B♭7", "D♭", "E♭", "A♭6", "B♭m7", "Bdim", "A♭", "C", "D♭7", "A♭6", "F7", "B♭7", "E♭7", "B", "B♭", "A", "A♭6", "A♭6", "F7", "B♭7", "E♭7", "B", "B♭", "A", "A♭6"]}