{"id": 53494, "song": "泣かないで聞いてくれ", "artist": "中村雅俊", "composer": "増田俊郎", "chord": ["F", "C", "E♭", "D7", "Gm", "B♭", "C", "F", "C", "Dm", "Gm", "Am", "Gm", "C", "F", "C", "E♭", "D7", "Gm", "B♭", "C", "F", "C", "Dm", "Gm", "Am7", "C", "B♭", "C", "F", "B♭", "C", "Dm", "Am", "Gm", "C", "F", "C", "E♭", "D7", "Gm", "B♭", "C", "F", "C", "Dm", "Gm", "Am", "Gm", "C", "F", "C", "E♭", "D7", "Gm", "B♭", "C", "F", "C", "Dm", "Gm", "Am7", "C", "B♭", "C", "F", "B♭", "C", "Dm", "Am", "Gm", "C", "F", "C", "E♭", "D7", "Gm", "B♭", "C", "F", "C", "Dm", "Gm", "Am", "Gm", "C", "Dm", "B♭", "C", "F", "A7", "Dm", "B♭", "A7", "Dm", "C", "B♭", "Gm7", "C", "F", "C", "E♭", "D7", "Gm", "B♭", "C", "F", "C", "Dm", "Gm", "Am", "Gm", "C", "F", "C", "E♭", "D7", "Gm", "B♭", "C", "F", "C", "Dm", "Gm", "B♭", "F", "F", "Gm", "Am", "B♭", "C", "B♭", "A", "A7", "Dm", "B♭", "C", "F", "Gm", "Am", "B♭", "C", "B♭", "A", "A7", "Dm", "B♭", "C", "F"]}