{"id": 40032, "song": "BATSU", "artist": "DADARAY", "composer": "川谷絵音", "chord": ["D♭", "B♭m", "Cm", "Fm", "E♭", "B♭m", "Fm", "E♭", "D♭", "Fm", "E♭", "B♭m", "Fm", "E♭", "D♭", "A♭", "Dm", "Bm", "D7", "F7", "E♭", "A♭", "Dm", "Bm", "D7", "F7", "E♭", "D♭", "Cm", "B♭m", "E♭", "D♭", "Cm", "Fm", "E♭", "Fm", "E♭", "B♭m", "Fm", "E♭", "D♭", "Fm", "E♭", "B♭m", "Fm", "E♭", "D♭", "B♭m", "Cm", "D♭", "Fm", "B♭m", "Cm", "D♭", "Fm", "B♭m", "Cm", "D♭", "Fm", "B♭m", "Cm", "D♭", "Fm", "Fm", "E♭", "B♭m", "Fm", "E♭", "B♭m", "Fm", "E♭", "D♭", "Fm", "E♭", "B♭m", "Fm", "E♭", "D♭", "Fm", "E♭", "B♭m", "Fm", "E♭", "D♭", "Fm", "E♭", "B♭m", "B♭m", "Fm", "E♭", "D♭", "Fm", "E♭", "B♭m", "Fm", "E♭", "D♭", "B♭m", "Cm", "Cm"]}