{"id": 98926, "song": "Shining Star-Garland Ver.-", "artist": "Rhodanthe*", "composer": "中塚武", "chord": ["E♭maj7", "Dm7", "Cm7", "F", "B♭maj7", "E♭maj7", "Dm7", "Cm7", "F", "Bmaj7", "N.C.", "E♭maj7", "Dm7", "Cm7", "F", "B♭maj7", "E♭maj7", "Dm7", "Cm7", "F", "Bmaj7", "N.C.", "Gm7", "G♭aug", "B♭", "F", "E♭m7", "Dm7", "D7", "Gm7", "Gm7", "F", "E♭maj7", "E♭m7", "F", "N.C.", "E♭maj7", "E♭m7", "Dm7", "D7", "Gm7", "Gm7", "F", "E♭maj7", "Dm7", "D7", "Gm7", "Cm7", "E♭", "F", "F", "C", "D", "D", "N.C.", "Gmaj7", "D", "G♭", "F6", "C", "E", "Cm", "G", "D♭m7-5", "Am7", "C", "D", "D", "N.C.", "E♭maj7", "Dm7", "Cm7", "F", "B♭maj7", "E♭maj7", "Dm7", "D♭m7", "G♭7+5", "N.C.", "Gm7", "G♭aug", "B♭", "F", "E♭m7", "Dm7", "D7", "Gm7", "Gm7", "F", "E♭maj7", "E♭m7", "F", "E♭maj7", "E♭m7", "Dm7", "D7", "Gm7", "Gm7", "F", "E♭maj7", "E♭maj7", "D7", "Gm7", "Cm7", "E♭", "F", "F", "C", "D", "D", "N.C.", "Gmaj7", "D", "G♭", "F6", "C", "E", "Cm", "G", "D♭m7-5", "Am7", "C", "D", "D", "N.C.", "E♭maj7", "Dm7", "Cm7", "D7", "Gm7", "G♭aug", "B♭", "F", "Em7-5", "E♭maj7", "D7", "Gm7", "C7sus4", "C7", "Cm7", "E♭", "F", "E♭maj7", "Dm7", "Cm7", "F", "Bmaj7", "E♭maj7", "Dm7", "Cm7", "F", "Bmaj7", "E♭maj7", "Dm7", "Cm7", "F", "Bmaj7", "Cm7", "Dm7", "E♭maj7", "E♭m7", "F", "A♭maj7", "Gm7", "G♭maj7", "E♭", "F", "F", "D7", "N.C.", "Gmaj7", "D", "G♭", "F6", "C", "E", "Cm", "G", "D♭m7-5", "Am7", "C", "D", "D", "Gmaj7", "D", "G♭", "F6", "C", "E", "Cm", "G", "D", "B7", "Em7", "Am7", "Bm7", "E♭dim", "Em7", "Cm7", "G", "D", "D♭m7-5", "Am7", "D", "N.C.", "Cmaj7", "Bm7", "Am7", "D", "Gmaj7", "Cmaj7", "Bm7", "Am7", "D", "Gmaj7", "Cmaj7", "Bm7", "Am7", "D", "Gmaj7", "Cmaj7", "Bm7", "A♭maj7", "N.C.", "Gmaj7"]}