{"id": 37212, "song": "誰のことを一番 愛してる?", "artist": "坂道AKB", "composer": "秋元康", "chord": ["C", "D", "Bm7", "Em", "C", "D", "Bm7", "Em", "Am7", "D", "D#dim", "Em", "C", "G", "D", "Em", "C", "D", "A#m", "F#", "C#", "G#", "A#m", "F#", "G#", "A#m", "F#", "C#", "G#", "A#m", "F#", "G#", "A#m", "F#", "C#", "G#", "A#m", "F#", "G#", "F#", "G#", "A#m", "F#", "G#", "F7", "Em", "C", "D", "G", "D#dim", "Em", "Am7", "D", "D#dim", "Em", "C", "D", "G", "D#dim", "C", "D", "Bm7", "Em", "C", "D", "Bm7", "Em", "Am7", "D", "D#dim", "Em", "C", "G", "D", "Em", "C", "D", "A#m", "F#", "C#", "G#", "A#m", "F#", "G#", "A#m", "F#", "C#", "F", "G#", "A#m", "F#", "G#", "A#m", "F#", "C#", "G#", "A#m", "F#", "G#", "F#", "G#", "A#m", "F#", "G#", "F7", "Em", "C", "D", "G", "D#dim", "Em", "Am7", "D", "D#dim", "Em", "C", "D", "G", "D#dim", "C", "D", "Bm7", "Em", "C", "D", "Bm7", "Em", "Am7", "D", "D#dim", "Em", "C", "G", "D", "Em", "C", "D", "A#m", "F#", "C#", "G#", "F#", "F7", "Em", "C", "D", "G", "D#dim", "Em", "Am7", "D", "D#dim", "Em", "C", "D", "G", "D#dim", "C", "D", "Bm7", "Em", "C", "D", "Bm7", "Em", "C", "D", "Bm7", "Em", "C", "D", "Bm7", "Em", "Am7", "D", "D#dim", "Em", "C", "G", "D", "Em", "C", "D", "A#m", "F#", "C#", "G#", "A#m", "F#", "G#", "A#m", "F#", "C#", "G#", "A#m", "F#", "G#", "A#m", "F#", "C#", "G#", "A#m", "F#", "G#"]}