{"id": 5155, "song": "行方不明", "artist": "GO!GO!7188", "composer": "中島優美", "chord": ["D♭m", "Dm", "D♭m", "Dm", "D♭m", "Dm", "G", "A", "Dm", "D♭m", "Dm", "D♭m", "Dm", "D♭m", "Dm", "G", "A", "Dm", "D♭m", "G", "A", "Dm", "A♭", "A", "Dm", "A♭", "A", "G", "A", "Dm", "G", "A", "Dm", "D♭m", "Dm", "G", "A", "Dm", "G", "A", "G", "A♭", "A", "Dm", "A♭", "A", "Dm", "A♭", "A", "G", "A", "Dm", "A♭", "A", "Dm", "A♭", "A", "G", "A", "Dm", "D♭m", "Dm", "G", "A", "Dm", "D♭m", "Dm", "G", "A♭", "A", "Dm", "A♭", "A", "Dm", "A♭", "A", "Dm", "A♭", "A", "Dm", "A♭", "A", "D♭m", "Dm", "D♭m", "Dm", "D♭m", "Dm", "D♭m", "Dm", "D♭m", "Dm", "D♭m", "Dm", "D♭m", "Dm", "G", "A", "Dm", "D♭m", "Dm", "D♭m", "Dm", "D♭m", "Dm", "G", "A", "Dm", "D♭m", "G", "A", "Dm", "A♭", "A", "Dm", "A♭", "A", "G", "A", "Dm", "G", "A", "Dm", "D♭m", "Dm", "G", "A", "Dm", "G", "A", "G", "A♭", "A", "Dm", "A♭", "A", "Dm", "A♭", "A", "G", "A", "Dm", "A♭", "A", "Dm", "A♭", "A", "G", "A", "Dm", "D♭m", "Dm", "G", "A", "Dm", "D♭m", "Dm", "G", "A♭", "A", "Dm", "Am", "B♭", "Gm", "Am", "F", "Gm", "C", "Dm", "Am", "B♭", "Gm", "Am", "F", "Gm", "C", "Dm", "Am", "B♭", "Gm", "Am", "F", "Gm", "C", "Dm", "Am", "B♭", "Gm", "Am", "F", "Gm", "C", "G", "A", "Dm", "G", "A", "Dm", "G", "A", "Dm", "B♭", "C", "A", "G", "A♭", "A", "G", "A♭", "A", "B♭", "A", "B♭", "A", "Dm", "A♭", "A", "Dm", "A♭", "A", "G", "A", "Dm", "A♭", "A", "Dm", "A♭", "A", "G", "A", "Dm", "D♭m", "Dm", "G", "A", "Dm", "D♭m", "Dm", "G", "A♭", "A", "G", "A", "Dm", "D♭m", "Dm", "G", "A♭", "A", "Dm", "A♭", "A", "Dm", "A♭", "A", "Dm", "A♭", "A", "Dm", "A♭", "A", "D♭m", "Dm", "D♭m", "Dm"]}