{"id": 57188, "song": "死ぬくらい大好き愛してるバカみたい", "artist": "HERE", "composer": "HERE", "chord": ["Bm", "G", "A", "Bm", "G", "A", "Bm", "G", "A", "Bm", "G", "A", "Bm", "G", "A", "Bm", "G", "A", "Em", "G", "Bm", "D", "Em", "G", "F#", "N.C", "Bm", "G", "A", "D", "Bm", "Em", "G", "A", "F#", "Bm", "Bm", "G", "A", "Bm", "G", "A", "Bm", "G", "A", "Bm", "G", "A", "Em", "G", "Bm", "D", "Em", "G", "F#", "N.C", "Bm", "G", "A", "D", "Bm", "Em", "G", "A", "F#", "Bm", "Bm", "F#", "Bm", "F#", "Bm", "F#", "Bm", "F#", "G", "F#", "Bm", "G", "A", "F#", "N.C", "F#", "Bm", "G", "A", "D", "Bm", "Em", "G", "A", "F#", "Bm", "Bm", "G", "A", "D", "Bm", "Em", "G", "A", "F#", "Bm", "Bm", "G", "A", "D", "Bm", "G", "A", "D", "Bm"]}