{"id": 57392, "song": "fruits", "artist": "坂口有望", "composer": "坂口有望", "chord": ["F", "A#", "F", "F", "A#", "F", "A#", "F", "A#", "F", "F", "A#", "C", "F", "C", "E", "A#", "F", "Gm", "C", "E", "F", "A#", "C", "F", "C", "E", "A#", "F", "Gm", "F", "A#", "C", "F", "C", "E", "A#", "F", "Gm", "C", "E", "F", "A#", "C", "F", "C", "E", "A#", "F", "Dm", "G", "A#", "F", "Dm", "G", "A#", "A#m", "F", "A#", "C", "A#", "Am", "Dm", "A#", "F", "G", "C", "F", "A#", "C", "A#", "Am", "Dm", "A#", "F", "G", "A#", "F", "Dm", "G", "N.C", "F", "F", "A#", "F", "A#", "C", "F", "C", "E", "A#", "F", "Gm", "C", "E", "F", "A#", "C", "F", "C", "E", "A#", "F", "Dm", "G", "A#", "F", "Dm", "G", "A#", "A#m", "F", "A#", "C", "A#", "Am", "Dm", "A#", "F", "G", "C", "F", "A#", "C", "A#", "Am", "Dm", "A#", "F", "G", "A#", "F", "Dm", "G", "N.C", "F", "F", "F", "A#", "C", "F", "C", "E", "A#", "A#m", "F", "Dm", "G", "A#", "F", "Dm", "G", "A#", "F", "Dm", "G", "A#", "F", "Dm", "G", "A#", "F", "C", "F", "A#", "C", "A#", "Am", "Dm", "A#", "F", "G", "C", "F", "A", "A#", "C", "A#", "Am", "Dm", "A#", "F", "G", "A#", "F", "Dm", "G", "N.C", "F", "F", "A#", "F", "A#", "F", "A#", "F", "A#", "F", "A#", "F"]}