{"id": 89997, "song": "Best Friend", "artist": "Goose house", "composer": "Goose house", "chord": ["F", "A", "B♭", "C", "Dm7", "Gm7", "Am7", "C", "F", "B♭", "Dm7", "B♭", "Gm7", "Am7", "B♭", "C", "F", "B♭", "F", "B♭", "F", "B♭", "Dm7", "C", "B♭", "C", "B♭", "Am7", "Dm7", "Gm7", "Am7", "B♭", "C", "Gm7", "Am7", "B♭", "C", "F", "B♭", "C", "A7", "Dm7", "F", "A", "B♭", "C", "F", "Dm7", "B♭", "C", "D♭dim", "Dm7", "F", "A", "B♭", "C", "B♭", "F", "A", "Gm7", "C", "F", "F", "A", "B♭", "F", "B♭", "C", "B♭", "Am7", "Dm7", "Gm7", "Am7", "B♭", "C", "Gm7", "Am7", "B♭", "C", "F", "B♭", "A", "A7", "Dm7", "F", "A", "B♭", "C", "F", "Dm7", "B♭", "C", "D♭dim", "Dm7", "F", "A", "B♭", "Csus4", "C", "F", "C", "E", "Dm7", "Dm7", "C", "B♭", "F", "A", "Gm7", "C", "C#dim", "Dm7", "C", "B♭", "F", "A", "Gm7", "C", "F", "B♭", "C", "F", "Dm7", "C", "B♭", "F", "A", "Gm7", "C", "E♭", "D♭", "G♭", "B", "D♭", "B♭7", "E♭m7", "G♭", "B♭", "B", "D♭", "G♭", "E♭m7", "B", "D♭", "Ddim", "E♭m7", "G♭", "B♭", "B", "D♭", "G♭", "B", "D♭", "E♭m7", "G♭", "B♭", "B", "D♭", "G♭"]}