{"id": 85879, "song": "サニー", "artist": "w.o.d.", "composer": "サイトウタクヤ", "chord": ["A♭", "C", "D♭", "A♭", "A♭", "C", "D♭", "A♭", "A♭", "C", "D♭", "A♭", "A♭", "C", "D♭", "A♭", "A♭", "C", "D♭", "A♭", "A♭", "C", "D♭", "A♭", "A♭", "C", "D♭", "A♭", "A♭", "C", "D♭", "A♭", "Cm", "A♭", "B", "A♭", "D♭", "Cm", "B", "B♭m", "A♭", "C", "D♭", "A♭", "A♭", "C", "D♭", "A♭", "A♭", "C", "D♭", "A♭", "A♭", "C", "D♭", "A♭", "A♭", "C", "D♭", "A♭", "A♭", "C", "D♭", "A♭", "A♭", "C", "D♭", "A♭", "A♭", "C", "D♭", "A♭", "A♭", "C", "D♭", "A♭", "A♭", "C", "D♭", "A♭", "Cm", "A♭", "B", "A♭", "D♭", "Cm", "B", "B♭m", "Cm", "A♭", "B", "A♭", "D♭", "Cm", "B", "D♭", "E♭", "Cm", "A♭", "B", "A♭", "D♭", "Cm", "B", "B♭m", "D♭", "Cm", "B", "B♭m", "A♭", "C", "D♭", "A♭", "A♭", "C", "D♭", "A♭", "A♭", "C", "D♭", "A♭", "A♭", "C", "D♭", "A♭"]}