{"id": 46894, "song": "バトン", "artist": "徳永英明", "composer": "徳永英明", "chord": ["E", "Am", "E", "Am", "E", "Am", "E", "E", "Am", "E", "E7", "C#", "F#m", "Am", "C#m", "Am", "B", "E", "Am", "E", "E", "Am", "E", "E7", "C#", "F#m", "Am", "C#m", "F#m7-5", "B", "A", "B", "E", "B", "E", "A", "B", "E", "B", "E", "A", "G#7", "C#m", "C#m7", "F#", "Am", "B", "A", "B", "E", "A", "G#7", "C#m", "E7", "C#", "F#m", "F#m7", "Am", "B", "E", "Am", "E", "Am", "E", "E", "Am", "E", "E7", "C#", "F#m", "Am", "C#m", "F#m", "B", "A", "B7", "E", "F#m", "E", "A", "G#7", "C#m", "E", "E7", "C#", "F#m", "F#m7", "Am", "B", "C#m", "A", "C#m", "A", "C#m", "A", "G#m", "F#", "Am", "B", "A", "B", "A", "B", "E", "B", "E", "A", "B", "E", "B", "E", "A", "G#7", "C#m", "F#", "Am", "B", "A", "B", "E", "F#m", "E", "A", "G#7", "C#m", "E", "E7", "C#", "F#m", "F#m7", "Am", "B", "E", "Am", "B", "E", "E", "F", "F#", "G", "G#", "E", "F", "F#", "G", "G#", "E", "F", "F#", "G", "G#", "E", "F", "F#", "G", "G#", "E", "F", "F#", "G", "G#", "E", "F", "F#", "G", "G#"]}