{"id": 96016, "song": "BROKEN", "artist": "BiSH", "composer": "井口イチロウ", "chord": ["Cadd9", "Fm", "Cadd9", "Fm", "Am7", "G", "F", "Fm", "Cadd9", "Fm", "Am7", "G", "F#m7-5", "G", "Cadd9", "Fm", "Am7", "G", "F#m7-5", "Fmaj7", "G", "F", "G", "C", "G", "B", "Am7", "Am7", "G", "Dm7", "Em7", "Fm", "G", "C", "G", "B", "Am7", "Gm7", "C", "Fmaj7", "G", "Em7", "A", "Fmaj7", "G", "C", "G", "B", "Am7", "Gm7", "C", "Fmaj7", "G", "Em7", "A", "Dm7", "Em7", "Fm", "G", "Cadd9", "Fm", "Am7", "G", "F", "Fm", "Cadd9", "Fm", "Am7", "G", "F#m7-5", "Fmaj7", "G", "F", "G", "C", "G", "B", "Am7", "Am7", "G", "Dm7", "Em7", "Fm", "G", "N.C.", "C", "G", "B", "Am7", "Gm7", "C", "Fmaj7", "G", "Em7", "A", "Dm7", "Em7", "Fm", "G", "F", "G", "C", "G", "B", "Am7", "Am7", "G", "Dm7", "Em7", "Fmaj7", "G", "N.C.", "N.C.", "C", "G", "B", "Am7", "Gm7", "C", "Fmaj7", "G", "Em7", "A7", "Fmaj7", "G", "C", "G", "B", "Am7", "Gm7", "C", "Fmaj7", "G", "Em7", "A", "Dm7", "Em7", "Fm", "G", "C", "Fm", "Am7", "G", "F", "Fm", "Cadd9"]}