{"id": 64009, "song": "heaven", "artist": "踊ってばかりの国", "composer": "下津光史", "chord": ["C", "F", "C", "F", "C", "F", "C", "F", "C", "F", "C", "F", "C", "F", "C", "F", "F", "Dm", "G", "F", "C", "F", "C", "Dm", "G", "N.C.", "C", "F", "Dm", "G", "C", "F", "Dm", "G", "E", "Am", "Dm", "G", "C", "F", "C", "F", "C", "F", "C", "F", "Dm", "G", "C", "Em7", "Am", "G", "Dm", "G", "C", "F", "Dm", "G", "C", "F", "Dm", "G", "A♭", "D♭", "G♭", "E♭m", "A♭", "D♭", "G♭", "E♭m", "A♭", "F", "B♭m", "E♭m", "A♭", "D♭", "G♭", "D♭", "G♭", "D♭", "G♭", "D♭", "G♭", "D♭"]}