{"id": 94130, "song": "highway, highway", "artist": "阿部芙蓉美", "composer": "阿部芙蓉美", "chord": ["E♭add9", "B♭", "D", "Csus4", "Cm7", "E♭add9", "B♭", "D", "Csus4", "Cm7", "E♭add9", "B♭", "D", "Csus4", "Cm7", "E♭add9", "B♭", "D", "Csus4", "A♭", "Gm7", "Cm7", "A♭", "B♭", "Gm7", "Cm7", "A♭", "E♭add9", "B♭", "D", "Csus4", "Cm7", "E♭add9", "B♭", "D", "Csus4", "Cm7", "E♭add9", "B♭", "D", "Csus4", "Cm7", "A♭", "B♭", "Gm7", "Cm7", "A♭", "B♭", "A♭", "E♭add9", "B♭", "D", "Csus4", "A♭", "E♭add9", "B♭", "D", "Csus4", "A♭", "E♭add9", "B♭", "D", "Csus4", "A♭", "E♭add9", "B♭", "D", "Csus4", "A♭", "E♭add9", "B♭", "D", "Csus4", "Cm7", "E♭add9", "B♭", "D", "Csus4", "Cm7", "Gm7", "Cm7", "A♭"]}