{"id": 9733, "song": "松田の子守唄", "artist": "サザンオールスターズ", "composer": "桑田佳祐", "chord": ["C", "G", "C", "F", "G", "C", "C", "G", "C", "F", "C", "G", "C", "F", "G", "C", "G", "C", "F", "G", "Am", "D7", "F", "D7", "E7", "Am", "D7", "Dm7", "G7", "C", "G", "F", "G", "C", "G", "F", "G", "Am", "D7", "F", "D7", "E7", "E7", "Am", "D7", "Dm7", "G7", "F", "G7", "C", "F", "G7", "C", "F", "G7", "C", "E7", "Am", "D7", "Dm7", "G7", "C", "G", "F", "G", "C", "G", "F", "G", "Am", "D7", "F", "D7", "E7", "Am", "D7", "Dm7", "G7", "F", "G7", "C", "F", "G7", "C", "F", "G7", "C", "E7", "Am", "D7", "Dm7", "G7", "C", "Cmaj7", "F", "C", "F", "C", "B♭", "C"]}