{"id": 501, "song": "スナフキン", "artist": "ゆず", "composer": "北川悠仁", "chord": ["C", "Dm7", "G", "C", "C", "Dm7", "G", "C", "G", "C", "Dm7", "G", "C", "C", "Dm7", "G", "C", "Dm7", "E7", "A7", "Dm7", "Fm", "G", "Am7", "G", "C", "A7", "F", "G", "C", "A7", "F", "G", "C", "G", "C", "Dm7", "G", "C", "C", "Dm7", "G", "C", "G", "C", "Dm7", "G", "C", "C", "Dm7", "G", "C", "Dm7", "E7", "A7", "Dm7", "Fm", "G", "Am7", "G", "C", "A7", "F", "G", "C", "A7", "F", "G", "C", "G", "C", "A7", "F", "G", "C", "A7", "F", "G", "C", "G", "C", "Dm7", "G", "C", "C", "Dm7", "G", "C"]}