{"id": 39794, "song": "Lemon Drops", "artist": "the pillows", "composer": "山中さわお", "chord": ["C", "Dm", "Em", "Dm", "C", "Dm", "Em", "Dm", "C", "Dm", "Em", "Dm", "C", "Dm", "Em", "Dm", "C", "Dm", "Em", "Dm", "C", "Dm", "Em", "Dm", "C", "Dm", "Em", "Dm", "C", "Dm", "Em", "Dm", "C", "Dm", "Em", "Dm", "C", "Dm", "Em", "F", "C", "Dm", "Em", "F", "C", "Dm", "Em", "F", "C", "Dm", "Em", "Dm", "C", "Dm", "Em", "Dm", "C", "Dm", "Em", "Dm", "C", "Dm", "Em", "Dm", "C", "Dm", "Em", "Dm", "C", "Dm", "Em", "F", "C", "Dm", "Em", "F", "C", "Dm", "Em", "F", "C", "B♭", "Am", "G", "C", "B♭", "Am", "G", "C", "Dm", "Em", "Dm", "C", "Dm", "Em", "F", "C", "Dm", "Em", "F", "C", "Dm", "Em", "F", "C", "Dm", "Em", "F", "C", "Dm", "Em", "F", "C", "C", "Dm", "Em", "Dm", "C", "Dm", "Em", "Dm", "C", "Dm", "Em", "Dm", "C", "Dm", "Em", "Dm", "C"]}