{"id": 69165, "song": "ハートブレイク", "artist": "藤井フミヤ", "composer": "布袋寅泰", "chord": ["F", "D♭aug", "Dm", "C", "B♭", "B♭m", "F", "F", "A", "B♭", "D♭", "E♭", "F", "A", "Dm", "F7", "B♭", "B♭m", "Am", "D", "Gm", "G", "C", "Caug", "F", "F", "A", "B♭", "D♭", "E♭", "F", "A", "Dm", "F7", "B♭", "B♭m", "Am", "D", "Gm", "G", "C", "Caug", "F", "D♭aug", "Dm", "C", "B♭", "B♭m", "F", "B♭", "F", "G♭", "E♭m", "A♭m", "D♭", "D♭7", "B♭m", "E♭", "A♭m", "D♭", "E♭", "F", "Dm", "Gm", "C", "C7", "Am", "D", "Gm", "C", "F", "B♭", "B♭m", "Am", "D", "Gm", "G", "C", "D", "G", "E♭aug", "Em", "D", "C", "Am", "D", "G", "E♭aug", "Em", "D", "C", "Cm", "G", "C", "G", "C", "G", "C", "G", "G", "B♭", "C", "D", "G", "G", "B♭", "C", "D", "G9", "F9", "G♭9", "G9"]}