{"id": 6929, "song": "そしてイニエスタ", "artist": "森山直太朗", "composer": "森山直太朗・御徒町凧", "chord": ["C", "G", "C", "Am7", "D7", "G", "Gsus4", "G", "G", "C", "D", "G", "D7", "G", "C", "D", "C", "G", "G", "C", "D", "G", "D7", "G", "C", "D", "C", "G", "Am7", "G", "C", "D", "G", "C", "D", "G", "G7", "C", "D", "G", "C", "Am", "D", "Em", "F", "D", "G", "C", "Am7", "D", "Em", "F", "D", "G", "C", "Am7", "D", "C", "D", "Bm", "Em", "C", "D", "G", "Gsus4", "G", "G", "C", "D", "G", "D7", "G", "C", "D", "C", "G", "Am7", "G", "C", "D", "G", "C", "D", "G", "G7", "C", "D", "G", "C", "Am", "D", "Em", "F", "D", "G", "C", "Am7", "D", "Em", "F", "D", "G", "C", "Am7", "D", "Em", "F", "D", "G", "C", "Am7", "D", "Em", "F", "D", "G", "C", "Am7", "D", "C", "D", "Bm", "Em", "C", "D", "G", "Gsus4", "G", "C", "G", "C", "Am7", "D7", "G", "Gsus4", "G"]}