{"id": 54898, "song": "でも生きている", "artist": "アイラヴミー", "composer": "さとうみほの", "chord": ["G", "D", "A", "Bm", "G", "D", "A", "Bm", "G", "D", "A", "Bm", "G", "D", "A", "Bm", "G", "D", "A", "Bm", "G", "D", "A", "Bm", "G", "D", "A", "Bm", "G", "D", "A", "Bm", "G", "D", "A", "Bm", "G", "D", "A", "Bm", "G", "D", "A", "Bm", "G", "D", "A", "Bm", "G", "D", "A", "Bm", "G", "D", "A", "Bm", "G", "D", "A", "Bm", "G", "D", "A", "Bm", "G", "D", "A", "Bm", "G", "D", "A", "Bm", "G", "D", "A", "Bm", "G", "D", "A", "Bm", "G", "D", "A", "Bm", "G", "D", "A", "Bm", "G", "D", "A", "Bm", "G", "D", "A", "Bm", "G", "D", "A", "Bm", "G", "D", "A", "Bm", "G", "D", "A", "Bm", "G", "D", "A", "Bm", "G", "D", "A", "Bm", "G", "D", "A", "Bm", "G", "D", "A", "Bm"]}