{"id": 89555, "song": "愛する人", "artist": "FOMARE", "composer": "FOMARE", "chord": ["B", "F#", "G#m", "F#", "E", "F#", "B", "F#", "B", "F#", "G#m", "F#", "E", "F#", "B", "F#", "G#m", "F#", "E", "F#", "B", "F#", "G#m", "F#", "E", "F#", "B", "F#", "G#m", "F#", "E", "F#", "D#m", "G#m", "E", "F#", "D#m", "G#m", "E", "F#", "B", "F#", "G#m", "F#", "E", "F#", "B", "F#", "G#m", "F#", "E", "F#", "E", "F#", "Gdim", "G#m", "E", "F#", "B", "F#", "G#m", "F#", "E", "F#", "B", "F#", "G#m", "F#", "E", "F#", "D#m", "G#m", "E", "F#", "D#m", "G#m", "E", "F#", "B", "F#", "G#m", "F#", "E", "F#", "B", "F#", "G#m", "F#", "E", "F#", "E", "F#", "Gdim", "G#m", "E", "F#", "E", "F#", "G#m", "B", "E", "F#", "G#m", "B", "E", "F#", "Gdim", "G#m", "E", "F#", "B", "F#", "B", "F#", "G#m", "F#", "E", "F#", "B", "F#", "G#m", "F#", "E", "F#", "E", "F#", "Gdim", "G#m", "E", "F#", "B", "F#", "G#m", "F#", "E", "F#", "B", "F#", "G#m", "F#", "E", "F#", "E", "F#", "Gdim", "G#m", "E", "F#", "B", "D#m", "E", "F#", "Gdim", "G#m", "E", "F#", "B", "F#", "B", "F#", "G#m", "F#", "E", "F#", "B", "F#", "G#m", "F#", "E", "F#", "E", "F#", "Gdim", "G#m", "E", "F#", "B", "D#m", "E", "F#", "Gdim", "G#m", "E", "F#", "B"]}