{"id": 50115, "song": "It Was In Me", "artist": "Avril Lavigne", "composer": "CHRISTY LAUREN, LAVIGNE AVRIL RAMONA, CARLSSON JOHAN JENS ERIK", "chord": ["D♭", "Fm", "E♭", "D♭", "Fm", "E♭", "B♭m", "D♭", "E♭", "B♭m", "D♭", "E♭", "B♭m", "D♭", "E♭", "B♭m", "D♭", "E♭", "B♭m", "D♭", "E♭", "B♭m", "D♭", "E♭", "B♭m", "D♭", "E♭", "B♭m", "D♭", "E♭", "A♭", "B♭m", "D♭", "A♭", "B♭m", "D♭", "A♭", "B♭m", "D♭", "Fm", "E♭", "D♭", "Fm", "E♭", "D♭", "D♭", "Fm", "E♭", "D♭", "Fm", "E♭", "B♭m", "D♭", "E♭", "B♭m", "D♭", "E♭", "B♭m", "D♭", "E♭", "B♭m", "D♭", "E♭", "A♭", "B♭m", "D♭", "A♭", "B♭m", "D♭", "A♭", "B♭m", "D♭", "Fm", "E♭", "D♭", "Fm", "E♭", "D♭", "D♭", "Fm", "E♭", "D♭", "Fm", "E♭", "D♭", "B♭m", "Fm", "A♭", "D♭", "A♭", "B♭m", "D♭", "A♭", "B♭m", "D♭", "A♭", "B♭m", "D♭", "Fm", "E♭", "D♭", "A♭", "B♭m", "D♭", "A♭", "B♭m", "D♭", "A♭", "B♭m", "D♭", "Fm", "E♭", "D♭", "Fm", "E♭", "D♭", "D♭", "Fm", "E♭", "D♭", "Fm", "E♭", "A♭"]}