{"id": 82868, "song": "お行儀の悪いことがしたい", "artist": "め組", "composer": "菅原達也", "chord": ["E♭", "B♭", "Cm", "A♭", "E♭", "B♭", "E♭", "B♭", "Cm", "E♭", "A♭", "E♭", "B♭", "E♭", "A♭", "B♭", "Gm", "Cm", "Fm", "B♭", "Cm", "E♭", "A♭", "E♭", "A♭", "E♭", "G♭dim", "G", "Cm", "E♭", "A♭", "E♭", "A♭", "E♭", "B♭", "E♭", "A♭", "B♭", "Gm", "Cm", "A♭", "E♭", "B♭", "E♭", "Cm", "E♭", "A♭", "E♭", "A♭", "E♭", "G♭dim", "G", "Cm", "E♭", "A♭", "E♭", "A♭", "E♭", "B♭", "E♭", "A♭", "E♭", "B♭", "E♭", "B♭", "Cm", "A♭", "E♭", "B♭", "E♭", "B♭", "Cm", "E♭", "A♭", "E♭", "B♭", "E♭", "A♭", "B♭", "Gm", "Cm", "Fm", "B♭", "G", "Cm", "E♭", "A♭", "E♭", "A♭", "E♭", "G♭dim", "G", "Cm", "E♭", "A♭", "E♭", "A♭", "E♭", "B♭", "E♭", "A♭", "B♭", "Gm", "Cm", "A♭", "E♭", "B♭", "E♭", "Cm", "E♭", "A♭", "E♭", "A♭", "E♭", "G♭dim", "G", "Cm", "E♭", "A♭", "E♭", "A♭", "E♭", "B♭", "E♭", "Cm", "E♭", "A♭", "E♭", "A♭", "E♭", "G♭dim", "G", "Cm", "E♭", "A♭", "E♭", "A♭", "E♭", "G♭dim", "G", "Cm", "E♭", "A♭", "E♭", "A♭", "E♭", "B♭", "E♭", "A♭", "B♭", "Gm", "Cm", "Fm", "B♭", "Cm", "E♭", "A♭", "E♭", "A♭", "E♭", "G♭dim", "G", "Cm", "E♭", "A♭", "E♭", "A♭", "E♭", "B♭", "E♭", "C#m", "E", "A", "E", "A", "E", "Gdim", "G#", "C#m", "E", "A", "E", "A", "E", "B", "E", "A", "B", "G#m", "C#m", "A", "E", "B", "E", "A", "B", "G#m", "C#m", "A", "E", "B", "E", "A", "B", "G#m", "C#m", "A", "E", "B", "E"]}