{"id": 10591, "song": "たばこのみ", "artist": "奥田民生", "composer": "奥田民生", "chord": ["G", "G", "Gm", "C", "Cm", "F7", "B♭", "B♭sus4", "B♭", "G", "Gm", "C", "Cm", "F7", "B♭", "B♭sus4", "B♭", "Cm", "A♭", "Cm6", "A♭", "E♭", "A♭", "B♭", "G", "G", "Gm", "C", "Cm", "F7", "B♭", "B♭sus4", "B♭", "G", "Gm", "C", "Cm", "F7", "B♭", "B♭sus4", "B♭", "Cm", "A♭", "Cm6", "A♭", "Cm", "A♭", "Cm6", "A♭", "Cm", "A♭", "Cm6", "A♭", "E♭", "A♭", "E♭", "A♭", "B♭", "B♭", "G7", "C7", "G7", "C7", "G7", "C7", "G7", "C7", "G7", "C7", "G7", "C7", "G7", "C7", "G7", "C7", "G7", "C7", "G7", "C7", "G7", "C7", "G7", "C7", "G7", "C7", "G7", "C7", "G7", "C7", "G7", "C7"]}