{"id": 32095, "song": "Into You (弾き語り向けアレンジ ver.)", "artist": "Ariana Grande", "composer": "Ariana Grande, Max Martin, Savan Kotecha, Alexander Kronlund & Ilya", "chord": ["N.C", "F#m", "A", "D", "E", "F#m", "A", "D", "E", "F#m", "A", "D", "D", "E", "F#m", "A", "D", "E", "F#m", "A", "D", "E", "F#m", "A", "D", "E", "F#m", "A", "D", "D", "E", "F#m", "A", "D", "E", "F#m", "A", "D", "E", "D", "E", "F#m", "F#m", "E", "G#", "A", "B", "D", "E", "F#m", "F#m", "E", "G#", "A", "E", "N.C", "F#m", "A", "D", "N.C", "F#m", "A", "D", "E", "F#m", "A", "D", "E"]}