{"id": 32096, "song": "Honey Bee feat.JOYSTICK(for h.g.p)", "artist": "Kalassy Nikoff", "composer": "RIMAZI", "chord": ["B♭", "F", "E♭", "F", "B♭", "F", "E♭", "F", "B♭", "F", "E♭", "F", "B♭", "F", "E♭", "F", "B♭", "F", "E♭", "F", "B♭", "F", "E♭", "F", "B♭", "F", "F", "E♭", "E♭", "F", "B♭", "B♭", "F", "F", "E♭", "E♭", "F", "B♭", "F", "E♭", "F", "B♭", "F", "E♭", "F", "B♭", "F", "E♭", "F", "B♭", "F", "E♭", "F", "B♭", "F", "F", "E♭", "E♭", "F", "B♭", "B♭", "F", "F", "E♭", "E♭", "F", "B♭", "F", "F", "E♭", "F", "F", "F", "B♭", "F", "E♭", "E♭", "F", "B♭", "F", "F", "F", "E♭", "F", "B♭", "B♭", "F", "F", "E♭", "F", "B♭", "B♭", "F", "F", "E♭", "E♭", "F", "B♭", "B♭", "F", "F", "E♭", "E♭", "F", "B♭", "F", "F", "E♭", "E♭", "F", "B♭", "B♭", "F", "F", "E♭", "E♭", "F", "B♭", "F", "E♭", "F", "B♭", "F", "E♭", "F", "B♭", "F", "E♭", "F", "B♭", "F", "E♭", "F"]}