{"id": 60989, "song": "Let it snow!", "artist": "DEAN FUJIOKA", "composer": "DEAN FUJIOKA", "chord": ["Emaj9", "D#7-9", "D#7", "G#m7", "C#m7", "Emaj9", "D#7-9", "D#7", "G#m7", "C#m7", "Emaj7", "D#m7", "F#", "G#", "C#m7", "Emaj7", "F#", "D#7", "G", "N.C", "Emaj7", "D#m7", "F#", "G#", "C#m7", "Emaj7", "F#", "D#7", "G", "G#m7", "Emaj7", "D#m7", "F#", "G#", "C#m7", "Emaj7", "F#", "D#7", "G", "G#m7", "Emaj7", "D#m7", "F#", "G#", "C#m7", "Emaj7", "F#", "D#7", "G", "G#m7", "Emaj9", "D#m7", "F#", "G#", "C#m7", "Emaj9", "F#", "G#dim", "G#m7", "Emaj9", "D#m7", "D#7", "F#", "G#", "C#m7", "Emaj9", "F#", "D#7", "G", "N.C", "Emaj7", "D#m7", "F#", "G#", "C#m7", "Emaj7", "F#", "D#7", "G", "G#m7", "N.C", "Emaj7", "D#m7", "F#", "G#", "C#m7", "Emaj7", "F#", "D#7", "G", "G#m7", "N.C", "Emaj7", "Badd9", "G#m7", "C#m9", "Emaj7", "Badd9", "D#7", "G", "G#m7", "Emaj7", "Badd9", "F#", "G#", "C#m9", "Emaj7", "Badd9", "D#7", "G", "N.C", "Emaj7", "D#m7", "F#", "G#", "C#m7", "Emaj7", "F#", "D#7", "G", "G#m7", "Emaj7", "D#m7", "F#", "G#", "C#m7", "Emaj7", "F#", "D#7", "G", "G#m7", "N.C", "D#m7", "F#", "G#", "C#m7", "Emaj7", "F#", "D#7", "G", "G#m7", "Emaj7", "D#m7", "F#", "G#", "C#m7", "Emaj7", "F#", "D#7", "G", "G#m7", "Emaj7", "D#m7", "F#", "G#", "C#m7", "Emaj7", "D#m7", "F#", "G#", "C#m7", "Emaj7", "D#m7", "F#", "G#", "C#m7", "Emaj7", "D#m7", "F#", "G#", "C#m7"]}