{"id": 83834, "song": "悋気な惑星", "artist": "そらる", "composer": "みきとP", "chord": ["G♭", "B♭m", "G♭", "B♭m", "G♭", "B♭m", "Gm7-5", "A♭sus4", "E♭m", "A♭", "B♭m", "D♭", "F", "G♭", "B♭m", "A♭", "E♭m", "A♭", "Adim", "B♭m", "B♭m7", "A♭", "E♭m", "Amaj7", "E♭m", "A♭", "B♭m", "D♭", "F", "G♭", "G♭", "B♭m", "G♭", "B♭m", "G♭", "B♭m", "Gm7-5", "A♭sus4", "E♭m", "A♭", "B♭m", "D♭", "F", "G♭", "B♭m", "A♭", "E♭m", "A♭", "Adim", "B♭m", "B♭m7", "A♭", "E♭m", "Amaj7", "G♭", "B♭m", "G♭", "B♭m", "G♭", "B♭m", "G♭", "B♭m", "G♭", "B♭m", "Gm7-5", "A♭sus4", "N.C.", "E♭m", "A♭", "B♭m", "D♭", "F", "G♭", "Adim", "D♭", "A♭", "E♭m", "A♭", "Adim", "B♭m", "B♭m7", "A♭", "E♭m", "Amaj7", "D♭", "A♭", "E♭", "G", "G♭", "D♭", "F", "G♭maj7", "Amaj7", "E♭m", "A♭", "B♭m", "D♭", "F", "G♭", "E♭m", "A♭", "B♭m", "D♭", "F", "G♭", "G♭", "B♭m"]}