{"id": 15958, "song": "Dear friends", "artist": "TRIPLANE", "composer": "江畑兵衛", "chord": ["G#m", "E", "B", "E", "F#7sus4", "Bsus4", "B", "G#m", "E", "B", "E", "G#m", "D#m", "E", "Bsus4", "B", "F#", "G#m", "D#m", "E", "F#", "G#m", "D#m", "E", "Bsus4", "B", "A#dim", "D#", "G#m", "Fm7-5", "C#m", "D#m", "G#sus4", "G#", "C#m", "F#", "B", "F#", "G#m", "F#", "E", "C#m", "D#7sus4", "D#", "G#m", "E", "B", "C#m", "F#", "B", "C#m", "D#m", "G#sus4", "G#", "G#m", "D#m", "E", "Bsus4", "B", "A#dim", "D#", "G#m", "Fm7-5", "C#m", "D#m", "G#sus4", "G#", "C#m", "F#", "B", "D#sus4", "D#", "G#m", "E", "B", "C#m", "F#", "B", "C#m", "D#m", "G#sus4", "G#", "Aadd9", "G#m", "F#m", "B", "A", "G#sus4", "G#", "C#m", "A", "E", "A", "B", "E", "B", "C#m", "A", "E", "A", "B", "C#sus4", "C#", "F#m", "A", "Bm7", "E", "A", "D", "E", "F#sus4", "F#", "Gdim", "G#m", "E", "B", "C#m", "F#", "B", "C#m", "D#m", "E", "F#", "D#", "G#m", "E", "B", "C#m", "F#", "B", "C#m", "D#m", "G#m", "E", "B", "E", "F#", "B", "F#", "G#m", "E", "B", "E", "F#sus4", "Badd9"]}