{"id": 47803, "song": "夫婦鏡", "artist": "殿さまキングス", "composer": "彩木雅夫", "chord": ["Cm", "Fm", "G", "Cm", "G", "Cm", "Cm", "Fm", "Cm", "Fm", "G", "Cm", "Fm", "Cm", "G", "Cm", "D", "Cm", "Fm", "G", "Cm", "G", "Cm", "Fm", "D", "G", "Cm", "Cm", "G#", "G7", "Cm", "G", "Cm", "Cm", "Fm", "Cm", "Fm", "G", "Cm", "Fm", "Cm", "G", "Cm", "D", "Cm", "Fm", "G", "Cm", "G", "Cm", "Fm", "D", "G", "Cm", "Cm", "Fm", "G", "Cm", "G7", "Cm", "Cm", "Fm", "Cm", "Fm", "G", "Cm", "Fm", "Cm", "G", "Cm", "D", "Cm", "Fm", "G", "Cm", "G", "Cm", "Fm", "D", "G", "Cm", "G", "Cm"]}