{"id": 54670, "song": "ラブソングを唄わない男", "artist": "怒髪天", "composer": "上原子友康", "chord": ["G", "Am", "G", "Am", "D", "G", "G", "Am", "D", "G", "G", "Am", "D", "G", "G", "Am", "D", "G", "G", "Am", "D", "G", "Cm", "G", "Cm", "Am", "D", "C", "D", "C", "D", "G", "C", "D", "G", "C", "D", "G", "Em", "Am", "D", "G", "C", "G", "G", "Am", "G", "Am", "D", "G", "G", "Am", "D", "G", "G", "Am", "D", "G", "G", "Am", "D", "G", "G", "Am", "D", "G", "Cm", "G", "Cm", "Am", "D", "C", "D", "C", "D", "G", "C", "D", "G", "C", "D", "G", "Em", "Am", "D", "Cm", "Cm", "G", "Cm", "Am", "D", "C", "D", "C", "D", "G", "C", "D", "G", "C", "D", "G", "Em", "Am", "D", "C", "D", "G", "C", "D", "G", "C", "D", "G", "Em", "Am", "D", "G", "E7", "Am", "D", "G", "G", "Am", "G", "Am", "D", "G", "Am", "G", "Am", "D", "G"]}