{"id": 27707, "song": "ブスにならない哲学", "artist": "ハロー!プロジェクトモベキマス", "composer": "つんく", "chord": ["E♭m7", "Bmaj7", "B♭m7", "A♭m7", "B♭m7", "Bmaj7", "Bmaj7", "B♭m7", "A♭m7", "B♭m7", "E♭m7", "Bmaj7", "B♭m7", "A♭m7", "B♭m7", "Bmaj7", "Bmaj7", "B♭m7", "A♭m7", "G♭maj7", "Emaj7", "B♭7", "A♭m7", "B♭7-9", "E♭m7", "A♭7", "Fm7", "B♭7", "E♭m7", "Emaj7", "E♭m7", "Adim", "Fm7", "B♭7", "B♭7", "A♭m7", "B♭7-9", "E♭m7", "A♭7", "Fm7", "B♭7", "E♭m7", "A♭m7", "B♭m7", "E♭m7", "A♭7", "Fm7", "B♭7", "E♭m7", "Fm7", "G♭maj7", "E♭m7", "Fm7-5", "B♭7", "E♭m7", "B♭7", "E♭m7", "Fm7-5", "B♭7", "E♭m7", "Fm7-5", "B♭7", "B7", "B♭7", "E♭m", "E♭m", "E♭m", "A♭m", "A♭m", "A♭m", "G♭", "B♭7", "B", "B♭7", "B7", "B♭7", "E♭m", "E♭m", "E♭m", "A♭m", "A♭m", "A♭m", "G♭", "B♭7", "B", "B♭sus4", "B♭7", "B♭sus4", "B♭7", "E♭m", "Bmaj7", "B♭m7", "A♭m7", "B♭m7", "Bmaj7", "Bmaj7", "B♭m7", "A♭m7", "B♭m7", "E♭m7", "Bmaj7", "B♭m7", "A♭m7", "B♭m7", "Bmaj7", "Bmaj7", "B♭m7", "A♭m7", "G♭maj7", "Emaj7", "B♭7", "A♭m7", "B♭7-9", "E♭m7", "A♭7", "Fm7", "B♭7", "E♭m7", "Emaj7", "E♭m7", "Adim", "Fm7", "B♭7", "B♭7", "A♭m7", "B♭7-9", "E♭m7", "A♭7", "Fm7", "B♭7", "E♭m7", "A♭m7", "B♭m7", "E♭m7", "A♭7", "Fm7", "B♭7", "E♭m7", "Fm7", "G♭maj7", "E♭m7", "Fm7-5", "B♭7", "E♭m7", "B♭7", "E♭m7", "Fm7-5", "B♭7", "E♭m7", "Fm7-5", "B♭7", "B7", "B♭7", "E♭m", "E♭m", "E♭m", "A♭m", "A♭m", "A♭m", "G♭", "B♭7", "B", "B♭7", "B7", "B♭7", "E♭m", "E♭m", "E♭m", "A♭m", "A♭m", "A♭m", "G♭", "B♭7", "B", "B♭sus4", "B♭7", "B♭sus4", "B♭7", "Emaj7", "Emaj7", "E♭m7", "Emaj7", "E♭m7", "A♭m7", "B♭m7", "Bmaj7", "E♭m7", "A♭m7", "B♭m7", "Bmaj7", "E♭m7", "A♭m7", "B♭m7", "Bmaj7", "E♭m7", "A♭m7", "B♭m7", "Bmaj7", "E♭m7", "E♭m", "E♭m", "E♭m", "A♭m", "A♭m", "A♭m", "G♭", "B♭7", "B", "B♭7", "B7", "B♭7", "E♭m", "E♭m", "E♭m", "A♭m", "A♭m", "A♭m", "G♭", "B♭7", "B", "B♭sus4", "B♭7", "B♭sus4", "B♭7", "Emaj7", "Bmaj7", "B♭m7", "A♭m7", "B♭m7", "Bmaj7", "Bmaj7", "B♭m7", "A♭m7", "B♭m7", "E♭m7", "Bmaj7", "B♭m7", "A♭m7", "B♭m7", "Bmaj7", "Bmaj7", "B♭m7", "A♭m7", "G♭maj7", "Emaj7"]}